wombat/__init__.py
wombat_ai-0.0.0.dist-info/LICENSE
wombat_ai-0.0.0.dist-info/METADATA
wombat_ai-0.0.0.dist-info/WHEEL
wombat_ai-0.0.0.dist-info/top_level.txt
wombat_ai-0.0.0.dist-info/RECORD
